MANIFEST.in
Makefile
README.md
python-yconfig.spec
setup.py
yconfig.py
yconfig.egg-info/PKG-INFO
yconfig.egg-info/SOURCES.txt
yconfig.egg-info/dependency_links.txt
yconfig.egg-info/top_level.txt