Metadata-Version: 1.1
Name: yconfig
Version: 0.2.1
Summary: Yet Another YAML configuration files manager for python
Home-page: https://github.com/jet9/python-yconfig
Author: Dmitry Kurbatov
Author-email: dk@dimcha.ru
License: BSD
Platform: UNKNOWN
Classifier: Development Status :: 4 - Beta
Classifier: Environment :: Console
Classifier: Intended Audience :: Developers
Classifier: License :: OSI Approved :: BSD License
Classifier: Operating System :: OS Independent
Classifier: Programming Language :: Python
Requires: ndict
Requires: PyYAML
